cyla_mixture/__init__.py
cyla_mixture/__main__.py
cyla_mixture/application.py
cyla_mixture-1.0.dist-info/LICENSE
cyla_mixture-1.0.dist-info/METADATA
cyla_mixture-1.0.dist-info/WHEEL
cyla_mixture-1.0.dist-info/entry_points.txt
cyla_mixture-1.0.dist-info/top_level.txt
cyla_mixture-1.0.dist-info/RECORD
